{
    "name":"Amazon Add Item to Cart Service",
    "code":"http://demo.fast.morfeo-project.org/gvsdata/resources/amazonAddItemToCartService.src.js",
    "creationDate":"2009-04-20T17:00:00+0100",
    "creator":"http://www.fabio.es/",
    "description":{
        "en-gb":"This service adds items to an Amazon shopping cart"
    },
    "domainContext":{
        "tags":[
            "amazon",
            "shopping",
            "cart"
        ],
        "user":"admin"
    },
    "homepage":"http://www.deri.ie/amazonAddItemToCartService",
    "icon":"http://demo.fast.morfeo-project.org/gvsdata/images/catalogue/amazonAddItemToCartService.png",
    "label":{
        "en-gb":"Add Item To Amazon Shopping Cart"
    },
    "rights":"http://creativecommons.org/",
    "screenshot":"http://www.deri.ie/amazonAddItemToCartService.jpg",
    "version":"1.0",
    "libraries":[
        {
            "language":"JavaScript",
            "source":"http://demo.fast.morfeo-project.org/gvsdata/amazonURL/signAmazonURLs.js"
        },
        {
            "language":"JavaScript",
            "source":"http://demo.fast.morfeo-project.org/gvsdata/amazonURL/jssha2/sha2.js"
        }
    ],
    "actions":[
        {
            "name":"add",
            "preconditions":[
                {
                    "id":"item",
                    "label":{
                        "en-gb":"An item"
                    },
                    "pattern":"?Item http://www.w3.org/1999/02/22-rdf-syntax-ns#type http://aws.amazon.com/AWSECommerceService#Item",
                    "positive":"true"
                }
            ],
            "uses":[
                {
                    "id":"cart",
                    "uri":"http://aws.amazon.com/AWSECommerceService#ShoppingCart"
                }
            ]
        }
    ],
    "postconditions":[
        [
            {
                "id":"cart",
                "label":{
                    "en-gb":"A shopping cart"
                },
                "pattern":"?Cart http://www.w3.org/1999/02/22-rdf-syntax-ns#type http://aws.amazon.com/AWSECommerceService#ShoppingCart",
                "positive":"true"
            },
            {
                "id":"message",
                "label":{
                    "en-gb":"A message"
                },
                "pattern":"?Message http://www.w3.org/1999/02/22-rdf-syntax-ns#type http://aws.amazon.com/AWSECommerceService#Message",
                "positive":"true"
            }
        ]
    ],
    "triggers":[
        "message"
    ]
}